oslo_versionedobjects/__init__.py
oslo_versionedobjects/_i18n.py
oslo_versionedobjects/_options.py
oslo_versionedobjects/_utils.py
oslo_versionedobjects/base.py
oslo_versionedobjects/exception.py
oslo_versionedobjects/fields.py
oslo_versionedobjects/fixture.py
oslo_versionedobjects/test.py
oslo_versionedobjects/examples/__init__.py
oslo_versionedobjects/examples/iot_bulb.py
oslo_versionedobjects/locale/en_GB/LC_MESSAGES/oslo_versionedobjects.po
oslo_versionedobjects/tests/__init__.py
oslo_versionedobjects/tests/obj_fixtures.py
oslo_versionedobjects/tests/test_exception.py
oslo_versionedobjects/tests/test_fields.py
oslo_versionedobjects/tests/test_fixture.py
oslo_versionedobjects/tests/test_objects.py
oslo_versionedobjects-3.7.0.dist-info/AUTHORS
oslo_versionedobjects-3.7.0.dist-info/LICENSE
oslo_versionedobjects-3.7.0.dist-info/METADATA
oslo_versionedobjects-3.7.0.dist-info/WHEEL
oslo_versionedobjects-3.7.0.dist-info/entry_points.txt
oslo_versionedobjects-3.7.0.dist-info/pbr.json
oslo_versionedobjects-3.7.0.dist-info/top_level.txt
oslo_versionedobjects-3.7.0.dist-info/RECORD
