Metadata-Version: 2.1
Name: oslo.versionedobjects
Version: 3.7.0
Summary: Oslo Versioned Objects library
Home-page: https://docs.openstack.org/oslo.versionedobjects/latest/
Author: OpenStack
Author-email: openstack-discuss@lists.openstack.org
Classifier: Environment :: OpenStack
Classifier: Intended Audience :: Information Technology
Classifier: Intended Audience :: System Administrators
Classifier: License :: OSI Approved :: Apache Software License
Classifier: Operating System :: POSIX :: Linux
Classifier: Programming Language :: Python
Classifier: Programming Language :: Python :: 3
Classifier: Programming Language :: Python :: 3.9
Classifier: Programming Language :: Python :: 3.10
Classifier: Programming Language :: Python :: 3.11
Classifier: Programming Language :: Python :: 3.12
Classifier: Programming Language :: Python :: 3 :: Only
Classifier: Programming Language :: Python :: Implementation :: CPython
Requires-Python: >=3.9
License-File: LICENSE
License-File: AUTHORS
Requires-Dist: oslo.concurrency >=3.26.0
Requires-Dist: oslo.config >=5.2.0
Requires-Dist: oslo.context >=2.19.2
Requires-Dist: oslo.messaging >=5.29.0
Requires-Dist: oslo.serialization >=2.18.0
Requires-Dist: oslo.utils >=7.4.0
Requires-Dist: oslo.log >=3.36.0
Requires-Dist: oslo.i18n >=3.15.3
Requires-Dist: WebOb >=1.7.1
Requires-Dist: netaddr >=0.7.18
